[
    {
        "scene": "2024-08-18-action-aria-sewing",
        "sequence": "000",
        "annotation": "Organize the content inside the sewing kit for easy access.\n",
        "start_frame_id": 0,
        "end_frame_id": 135
    },
    {
        "scene": "2024-08-18-action-aria-sewing",
        "sequence": "001",
        "annotation": "Grasp the scissors for cutting.\n",
        "start_frame_id": 0,
        "end_frame_id": 74
    },
    {
        "scene": "2024-08-18-action-aria-sewing",
        "sequence": "002",
        "annotation": "Cut the eyes, mouth and other parts aligning the cutting line.\n",
        "start_frame_id": 0,
        "end_frame_id": 4906
    },
    {
        "scene": "2024-08-18-action-aria-sewing",
        "sequence": "003",
        "annotation": "Stick the eyes and other parts on the face of the planet.\n",
        "start_frame_id": 0,
        "end_frame_id": 2534
    },
    {
        "scene": "2024-08-18-action-aria-sewing",
        "sequence": "004",
        "annotation": "Unwrap the thread the spool.\n",
        "start_frame_id": 0,
        "end_frame_id": 239
    },
    {
        "scene": "2024-08-18-action-aria-sewing",
        "sequence": "005",
        "annotation": "Gently untangle any knot thread using both hands.\n",
        "start_frame_id": 0,
        "end_frame_id": 315
    },
    {
        "scene": "2024-08-18-action-aria-sewing",
        "sequence": "006",
        "annotation": "Tie the thread to the needle.\n",
        "start_frame_id": 0,
        "end_frame_id": 1640
    },
    {
        "scene": "2024-08-18-action-aria-sewing",
        "sequence": "007",
        "annotation": "Sew the fabric pieces together with the needle through the holes while leaving a little space for stuffing.\n",
        "start_frame_id": 0,
        "end_frame_id": 4327
    },
    {
        "scene": "2024-08-18-action-aria-sewing",
        "sequence": "008",
        "annotation": "Continue stitching the pieces of fabric together",
        "start_frame_id": 0,
        "end_frame_id": 4042
    },
    {
        "scene": "2024-08-18-action-aria-sewing",
        "sequence": "009",
        "annotation": "Continue sticking the pieces of fabric together",
        "start_frame_id": 0,
        "end_frame_id": 2437
    },
    {
        "scene": "2024-08-18-action-aria-sewing",
        "sequence": "010",
        "annotation": "Continue sticking the pieces of fabric together",
        "start_frame_id": 0,
        "end_frame_id": 502
    },
    {
        "scene": "2024-08-18-action-aria-sewing",
        "sequence": "011",
        "annotation": "Fill the planet with cotton.\n",
        "start_frame_id": 0,
        "end_frame_id": 1935
    },
    {
        "scene": "2024-08-18-action-aria-sewing",
        "sequence": "012",
        "annotation": "Stitch the little space together.\n",
        "start_frame_id": 0,
        "end_frame_id": 839
    },
    {
        "scene": "2024-08-18-action-aria-sewing",
        "sequence": "013",
        "annotation": "Knot the end of the thread to secure the cottons.\n",
        "start_frame_id": 0,
        "end_frame_id": 298
    },
    {
        "scene": "2024-08-18-action-aria-sewing",
        "sequence": "014",
        "annotation": "Untie the thread from the needle",
        "start_frame_id": 0,
        "end_frame_id": 93
    },
    {
        "scene": "2024-08-18-action-aria-sewing",
        "sequence": "015",
        "annotation": "Puncture the used needle into the futon.\n",
        "start_frame_id": 0,
        "end_frame_id": 112
    },
    {
        "scene": "2024-08-18-action-aria-sewing",
        "sequence": "016",
        "annotation": "Cut the excess thread with the scissors.\n",
        "start_frame_id": 0,
        "end_frame_id": 355
    },
    {
        "scene": "2024-08-18-action-aria-sewing",
        "sequence": "017",
        "annotation": "Pick up the yarn and the crochet hook.\n",
        "start_frame_id": 0,
        "end_frame_id": 95
    },
    {
        "scene": "2024-08-18-action-aria-sewing",
        "sequence": "018",
        "annotation": "Make a slip knot by forming a loop with the yarn. Insert the crochet hook into the loop. Pull the working yarn through the loop.\n",
        "start_frame_id": 0,
        "end_frame_id": 545
    },
    {
        "scene": "2024-08-18-action-aria-sewing",
        "sequence": "019",
        "annotation": "Yarn over by wrapping the yarn around the hook from back to front.\n",
        "start_frame_id": 0,
        "end_frame_id": 110
    },
    {
        "scene": "2024-08-18-action-aria-sewing",
        "sequence": "020",
        "annotation": "Pull the yarn through the loop on the hook to create a chain stitch.\n",
        "start_frame_id": 0,
        "end_frame_id": 93
    },
    {
        "scene": "2024-08-18-action-aria-sewing",
        "sequence": "021",
        "annotation": "Repeat the yarn over and pull through steps to create 10 chain stitches for the foundation.\n",
        "start_frame_id": 0,
        "end_frame_id": 1385
    },
    {
        "scene": "2024-08-18-action-aria-sewing",
        "sequence": "022",
        "annotation": "Crochet a single row.\n",
        "start_frame_id": 0,
        "end_frame_id": 2119
    },
    {
        "scene": "2024-08-18-action-aria-sewing",
        "sequence": "023",
        "annotation": "Cut the yarn, leaving a tail.\n",
        "start_frame_id": 0,
        "end_frame_id": 237
    },
    {
        "scene": "2024-08-18-action-aria-sewing",
        "sequence": "024",
        "annotation": "Weave in ends of yarn or thread using the hook.",
        "start_frame_id": 0,
        "end_frame_id": -1
    }
]